mofaflex/__init__.py
mofaflex/_version.py
mofaflex/_core/__init__.py
mofaflex/_core/feature_sets.py
mofaflex/_core/gp.py
mofaflex/_core/io.py
mofaflex/_core/mofaflex.py
mofaflex/_core/pcgse.py
mofaflex/_core/preprocessing.py
mofaflex/_core/presets.py
mofaflex/_core/settings.py
mofaflex/_core/training.py
mofaflex/_core/utils.py
mofaflex/_core/datasets/__init__.py
mofaflex/_core/datasets/anndatadictdataset.py
mofaflex/_core/datasets/base.py
mofaflex/_core/datasets/misc.py
mofaflex/_core/datasets/mudatadataset.py
mofaflex/_core/datasets/utils.py
mofaflex/_core/likelihoods/__init__.py
mofaflex/_core/likelihoods/base.py
mofaflex/_core/likelihoods/bernoulli.py
mofaflex/_core/likelihoods/negativebinomial.py
mofaflex/_core/likelihoods/normal.py
mofaflex/_core/pyro/__init__.py
mofaflex/_core/pyro/dist.py
mofaflex/_core/pyro/model.py
mofaflex/_core/pyro/utils.py
mofaflex/_core/pyro/likelihoods/__init__.py
mofaflex/_core/pyro/likelihoods/base.py
mofaflex/_core/pyro/likelihoods/bernoulli.py
mofaflex/_core/pyro/likelihoods/categorical.py
mofaflex/_core/pyro/likelihoods/negativebinomial.py
mofaflex/_core/pyro/likelihoods/normal.py
mofaflex/_core/pyro/priors/__init__.py
mofaflex/_core/pyro/priors/base.py
mofaflex/_core/pyro/priors/gaussian_process.py
mofaflex/_core/pyro/priors/horseshoe.py
mofaflex/_core/pyro/priors/simple_location_scale.py
mofaflex/_core/pyro/priors/spike_slab.py
mofaflex/pl/__init__.py
mofaflex/pl/_plotting.py
mofaflex/tl/__init__.py
mofaflex/tl/_downstream.py
mofaflex/tl/_gpu.py
mofaflex/tl/_msigdb.py
mofaflex/tl/_synthetic.py
mofaflex-0.1.0.post1.dist-info/METADATA
mofaflex-0.1.0.post1.dist-info/WHEEL
mofaflex-0.1.0.post1.dist-info/licenses/LICENSE
mofaflex-0.1.0.post1.dist-info/RECORD
