Metadata-Version: 2.4
Name: mofaflex
Version: 0.1.0.post1
Summary: Factor Analysis Models
Project-URL: Documentation, https://mofaflex.readthedocs.io/
Project-URL: Home-page, https://github.com/bioFAM/mofaflex
Project-URL: Source, https://github.com/bioFAM/mofaflex
Author-email: Ilia Kats <i.kats@dkfz.de>, Arber Qoku <arber.qoku@dkfz.de>, Florin Walter <florin.walter@dkfz.de>, Martin Rohbeck <martin.rohbeck@dkfz.de>
Maintainer-email: Ilia Kats <i.kats@dkfz.de>
License: BSD 3-Clause License
License-File: LICENSE
Classifier: Programming Language :: Python :: 3 :: Only
Classifier: Programming Language :: Python :: 3.11
Classifier: Programming Language :: Python :: 3.12
Classifier: Programming Language :: Python :: 3.13
Classifier: Programming Language :: Python :: 3.14
Requires-Python: >=3.11
Requires-Dist: anndata>=0.11
Requires-Dist: array-api-compat
Requires-Dist: dtw-python
Requires-Dist: gpytorch
Requires-Dist: h5py
Requires-Dist: mizani
Requires-Dist: mudata>=0.3.2
Requires-Dist: numpy
Requires-Dist: packaging
Requires-Dist: pandas
Requires-Dist: platformdirs
Requires-Dist: plotnine
Requires-Dist: pyro-ppl
Requires-Dist: scikit-learn
Requires-Dist: scipy>=1.8
Requires-Dist: session-info2
Requires-Dist: statsmodels
Requires-Dist: torch
Requires-Dist: tqdm
Provides-Extra: dev
Requires-Dist: pre-commit; extra == 'dev'
Requires-Dist: twine>=4.0.2; extra == 'dev'
Provides-Extra: doc
Requires-Dist: docutils!=0.18.*,!=0.19.*,>=0.8; extra == 'doc'
Requires-Dist: ipykernel; extra == 'doc'
Requires-Dist: ipython; extra == 'doc'
Requires-Dist: myst-nb>=1.1; extra == 'doc'
Requires-Dist: pandas; extra == 'doc'
Requires-Dist: setuptools; extra == 'doc'
Requires-Dist: sphinx-autodoc-typehints; extra == 'doc'
Requires-Dist: sphinx-automodapi; extra == 'doc'
Requires-Dist: sphinx-book-theme>=1; extra == 'doc'
Requires-Dist: sphinx-copybutton; extra == 'doc'
Requires-Dist: sphinx-tabs; extra == 'doc'
Requires-Dist: sphinx>=8.1; extra == 'doc'
Requires-Dist: sphinxcontrib-bibtex>=1; extra == 'doc'
Requires-Dist: sphinxext-opengraph; extra == 'doc'
Provides-Extra: lazy
Requires-Dist: dask[array,dataframe]!=2025.5; extra == 'lazy'
Provides-Extra: test
Requires-Dist: coverage>=7.10; extra == 'test'
Requires-Dist: dask[array,dataframe]!=2025.5; extra == 'test'
Requires-Dist: pytest; extra == 'test'
